pyg_npy/__init__.py
pyg_npy/_file.py
pyg_npy/_npy.py
pyg_npy-0.0.9.dist-info/LICENSE
pyg_npy-0.0.9.dist-info/METADATA
pyg_npy-0.0.9.dist-info/WHEEL
pyg_npy-0.0.9.dist-info/top_level.txt
pyg_npy-0.0.9.dist-info/RECORD
