Metadata-Version: 2.1
Name: pyg-npy
Version: 0.0.9
Summary: Utilities for data manipulation including creation of DAGs and tables
Home-page: https://github.com/gityoav/pyg-npy
Author: Yoav Git
Author-email: yoav.git@gmail.com
Project-URL: Bug Tracker, https://github.com/gityoav/pyg-npy/issues
Classifier: Programming Language :: Python :: 3
Classifier: License :: OSI Approved :: GNU General Public License v3 (GPLv3)
Classifier: Operating System :: OS Independent
Requires-Python: >=3.6
License-File: LICENSE
Requires-Dist: numpy
Requires-Dist: pandas
